python_cli_app_template/__init__.py
python_cli_app_template/_version.py
python_cli_app_template/config.py
python_cli_app_template/cli/__init__.py
python_cli_app_template/cli/config.py
python_cli_app_template/cli/factorial.py
python_cli_app_template/cli/main.py
python_cli_app_template/cli/prime.py
python_cli_app_template/defaults/settings.pca.toml
python_cli_app_template-0.3.0.dist-info/METADATA
python_cli_app_template-0.3.0.dist-info/WHEEL
python_cli_app_template-0.3.0.dist-info/entry_points.txt
python_cli_app_template-0.3.0.dist-info/licenses/AUTHORS.md
python_cli_app_template-0.3.0.dist-info/licenses/LICENSE.txt
python_cli_app_template-0.3.0.dist-info/RECORD
