Metadata-Version: 2.3
Name: python-cli-app-template
Version: 0.3.0
Summary: Python CLI app template project featuring the modern and extensible Python project manager hatch.
Project-URL: Documentation, https://turbobasic.github.io/python-cli-app-template
Project-URL: Source, https://github.com/turboBasic/python-cli-app-template
Project-URL: Tracker, https://github.com/turboBasic/python-cli-app-template/issues
Author-email: Andrii Melnyk ⚡️ <andrii7melnyk@proton.me>
License: MIT
License-File: AUTHORS.md
License-File: LICENSE.txt
Keywords: hatch,typer
Classifier: Development Status :: 2 - Pre-Alpha
Classifier: Programming Language :: Python
Classifier: Programming Language :: Python :: 3.11
Classifier: Programming Language :: Python :: 3.12
Classifier: Programming Language :: Python :: Implementation :: CPython
Requires-Python: >=3.11
Requires-Dist: dynaconf
Requires-Dist: sympy
Requires-Dist: typer
